jbtuner2_manager/__init__.py
jbtuner2_manager/__main__.py
jbtuner2_manager/espota.py
jbtuner2_manager/main.py
jbtuner2_manager-0.1.5.dist-info/entry_points.txt
jbtuner2_manager-0.1.5.dist-info/WHEEL
jbtuner2_manager-0.1.5.dist-info/METADATA
jbtuner2_manager-0.1.5.dist-info/RECORD
