Metadata-Version: 2.1
Name: jbtuner2-manager
Version: 0.1.5
Summary: An integrated tool for managing ChordX JBTuner2
Author: Ying Shaodong
Author-email: gavin.ying@chordx.co
Requires-Python: >=3.7,<4.0
Classifier: Programming Language :: Python :: 3
Classifier: Programming Language :: Python :: 3.7
Classifier: Programming Language :: Python :: 3.8
Classifier: Programming Language :: Python :: 3.9
Requires-Dist: typer[all] (>=0.3.2,<0.4.0)
